Himpunan_Logic/__init__.py
Himpunan_Logic/himpunan.py
afl2_kelompok5_himpunan-1.0.1.dist-info/METADATA
afl2_kelompok5_himpunan-1.0.1.dist-info/WHEEL
afl2_kelompok5_himpunan-1.0.1.dist-info/top_level.txt
afl2_kelompok5_himpunan-1.0.1.dist-info/RECORD
