Metadata-Version: 2.4
Name: AFL2_Kelompok5_Himpunan
Version: 1.0.1
Summary: Mini Project II: Implementasi Himpunan dengan Bahasa Pemrogramman Python
Home-page: https://github.com/VivianWijaya06/Himpunan_Kelompok5
Author: Kelompok 5
Author-email: vwijaya11@student.ciputra.ac.id, christianlaury01@student.ciputra.ac.id, rfebrian01@student.ciputra.ac.id
Classifier: Programming Language :: Python :: 3
Classifier: Operating System :: OS Independent
Classifier: Topic :: Education
Requires-Python: >=3.6
Dynamic: author
Dynamic: author-email
Dynamic: classifier
Dynamic: description
Dynamic: description-content-type
Dynamic: home-page
Dynamic: requires-python
Dynamic: summary
